project_logger/.env
project_logger/__init__.py
project_logger/api_client.py
project_logger/constants.py
project_logger/db.py
project_logger/example_usage.py
project_logger/exceptions.py
project_logger/security.py
project_logger/utils.py
project_logger/pyarmor_runtime_000000/__init__.py
project_logger/pyarmor_runtime_000000/pyarmor_runtime.pyd
project_logger-1.4.0.dist-info/LICENSE
project_logger-1.4.0.dist-info/METADATA
project_logger-1.4.0.dist-info/WHEEL
project_logger-1.4.0.dist-info/top_level.txt
project_logger-1.4.0.dist-info/RECORD
