Metadata-Version: 2.1
Name: project-logger
Version: 1.4.0
Summary: A security logging package for Python projects
Home-page: UNKNOWN
Author: Funnel
Author-email: sunn61676@gmail.com
License: UNKNOWN
Platform: UNKNOWN
Classifier: Programming Language :: Python :: 3
Classifier: License :: OSI Approved :: MIT License
Classifier: Operating System :: OS Independent
Requires-Python: >=3.6
License-File: LICENSE
Requires-Dist: pymysql
Requires-Dist: dbutils
